rrprettier/__init__.py
rrprettier2-1.0.0.dist-info/LICENSE
rrprettier2-1.0.0.dist-info/METADATA
rrprettier2-1.0.0.dist-info/WHEEL
rrprettier2-1.0.0.dist-info/RECORD
